nashpobench2api/__init__.py
nashpobench2api/api.py
nashpobench2api/utils.py
nashpobench2api-1.0.0.dist-info/LICENSE
nashpobench2api-1.0.0.dist-info/METADATA
nashpobench2api-1.0.0.dist-info/WHEEL
nashpobench2api-1.0.0.dist-info/top_level.txt
nashpobench2api-1.0.0.dist-info/RECORD
