Metadata-Version: 2.1
Name: nashpobench2api
Version: 1.0.0
Summary: API for NAS-HPO-Bench-II.
Home-page: https://github.com/yoichii/nashpobench2api
Author: Yoichi Hirose
License: MIT
Platform: UNKNOWN
License-File: LICENSE
